azure_functions_devops_build/__init__.py
azure_functions_devops_build/constants.py
azure_functions_devops_build/exceptions.py
azure_functions_devops_build/artifact/__init__.py
azure_functions_devops_build/artifact/artifact_manager.py
azure_functions_devops_build/base/__init__.py
azure_functions_devops_build/base/base_github_manager.py
azure_functions_devops_build/base/base_manager.py
azure_functions_devops_build/builder/__init__.py
azure_functions_devops_build/builder/builder_manager.py
azure_functions_devops_build/extension/__init__.py
azure_functions_devops_build/extension/extension_manager.py
azure_functions_devops_build/organization/__init__.py
azure_functions_devops_build/organization/organization_manager.py
azure_functions_devops_build/organization/models/__init__.py
azure_functions_devops_build/organization/models/new_organization.py
azure_functions_devops_build/organization/models/organization_details.py
azure_functions_devops_build/organization/models/organizations.py
azure_functions_devops_build/organization/models/region_details.py
azure_functions_devops_build/organization/models/regions.py
azure_functions_devops_build/organization/models/validate_account_name.py
azure_functions_devops_build/pool/__init__.py
azure_functions_devops_build/pool/pool_manager.py
azure_functions_devops_build/pool/models/__init__.py
azure_functions_devops_build/pool/models/pool_details.py
azure_functions_devops_build/pool/models/pool_details_depth.py
azure_functions_devops_build/pool/models/pools.py
azure_functions_devops_build/project/__init__.py
azure_functions_devops_build/project/project_manager.py
azure_functions_devops_build/project/models/__init__.py
azure_functions_devops_build/project/models/project_details.py
azure_functions_devops_build/project/models/project_failed.py
azure_functions_devops_build/project/models/project_poll.py
azure_functions_devops_build/project/models/projects.py
azure_functions_devops_build/release/__init__.py
azure_functions_devops_build-0.0.21.dist-info/DESCRIPTION.rst
azure_functions_devops_build-0.0.21.dist-info/METADATA
azure_functions_devops_build-0.0.21.dist-info/RECORD
azure_functions_devops_build-0.0.21.dist-info/WHEEL
azure_functions_devops_build-0.0.21.dist-info/metadata.json
azure_functions_devops_build-0.0.21.dist-info/top_level.txt
