Metadata-Version: 2.0
Name: azure-functions-devops-build
Version: 0.0.21
Summary: Python package for integrating Azure Functions with Azure DevOps. Specifically made for the Azure CLI
Home-page: https://github.com/Azure/azure-functions-devops-build
Author: Oliver Dolk, Hanzhang Zeng
Author-email: t-oldolk@microsoft.com, hazeng@microsoft.com
License: MIT
Keywords: Microsoft,Azure DevOps,Azure Functions,Azure Pipelines
Platform: UNKNOWN
Requires-Dist: msrest
Requires-Dist: vsts
Requires-Dist: jinja2
